[{"filename": "NEW-ShowFilled", "similarity": 1.0}, {"filename": "OLD-ShowFilled", "similarity": 0.9999}, {"filename": "OLD-CirclePlusOutlineFilled", "similarity": 0.8862}, {"filename": "NEW-CirclePlusOutlineFilled", "similarity": 0.8862}, {"filename": "NEW-InfoFilled", "similarity": 0.8794}, {"filename": "OLD-InfoFilled", "similarity": 0.8794}, {"filename": "OLD-AlertFilled", "similarity": 0.8794}, {"filename": "NEW-AlertFilled", "similarity": 0.8794}, {"filename": "OLD-ToggleFilled", "similarity": 0.8628}, {"filename": "NEW-ToggleFilled", "similarity": 0.8628}, {"filename": "NEW-CircleTickFilled", "similarity": 0.8516}, {"filename": "OLD-CircleTickFilled", "similarity": 0.8516}, {"filename": "OLD-PlayFilled", "similarity": 0.8513}, {"filename": "OLD-BundleSalesFilled1Outlined", "similarity": 0.8511}, {"filename": "NEW-ChatFilled", "similarity": 0.8501}, {"filename": "OLD-ChatFilled", "similarity": 0.8501}, {"filename": "NEW-ClokcFilled", "similarity": 0.8438}, {"filename": "OLD-ClokcFilled", "similarity": 0.8438}, {"filename": "OLD-DuplicateFilled", "similarity": 0.838}, {"filename": "NEW-DuplicateFilled", "similarity": 0.838}, {"filename": "NEW-LogoListFilled", "similarity": 0.8321}, {"filename": "OLD-LogoListFilled", "similarity": 0.832}, {"filename": "OLD-MultiCurrencyFilled", "similarity": 0.8311}, {"filename": "NEW-ColorFilled", "similarity": 0.8293}, {"filename": "OLD-ColorFilled", "similarity": 0.8293}, {"filename": "OLD-SendOutlined", "similarity": 0.829}, {"filename": "OLD-MarketingFilled", "similarity": 0.8266}, {"filename": "NEW-MarketingFilled", "similarity": 0.8266}, {"filename": "NEW-CircleRightFilled", "similarity": 0.8256}, {"filename": "OLD-CircleRightFilled", "similarity": 0.8256}]