[{"filename": "OLD-Transfer", "similarity": 1.0}, {"filename": "NEW-Transfer", "similarity": 1.0}, {"filename": "OLD-ArrowRight", "similarity": 0.8617}, {"filename": "NEW-ArrowRight", "similarity": 0.8617}, {"filename": "NEW-ArrowLeft", "similarity": 0.8572}, {"filename": "OLD-ArrowLeft", "similarity": 0.8572}, {"filename": "OLD-Back", "similarity": 0.8572}, {"filename": "OLD-ToTop", "similarity": 0.8032}, {"filename": "NEW-ToTop", "similarity": 0.8032}, {"filename": "OLD-Search", "similarity": 0.8028}, {"filename": "NEW-Search", "similarity": 0.8028}, {"filename": "OLD-Withdraw", "similarity": 0.797}, {"filename": "NEW-ColorDropper", "similarity": 0.7956}, {"filename": "OLD-ColorDropper", "similarity": 0.7956}, {"filename": "OLD-ToggleFilled", "similarity": 0.7909}, {"filename": "NEW-ToggleFilled", "similarity": 0.7909}, {"filename": "OLD-ShipmentFilled", "similarity": 0.7854}, {"filename": "NEW-ShipmentFilled", "similarity": 0.7854}, {"filename": "OLD-Folder", "similarity": 0.7794}, {"filename": "OLD-BulkEdit", "similarity": 0.7792}, {"filename": "OLD-ExpandMenu", "similarity": 0.7733}, {"filename": "OLD-Export", "similarity": 0.7729}, {"filename": "NEW-Export", "similarity": 0.7729}, {"filename": "OLD-CollectionsFilled", "similarity": 0.7726}, {"filename": "NEW-CollectionsFilled", "similarity": 0.7726}, {"filename": "OLD-Payments", "similarity": 0.7708}, {"filename": "NEW-Payments", "similarity": 0.7707}, {"filename": "OLD-RevocationTheme", "similarity": 0.7707}, {"filename": "OLD-ExpandMenuLeft", "similarity": 0.7691}, {"filename": "OLD-Attachment", "similarity": 0.7671}]