[{"filename": "NEW-VS", "similarity": 1.0}, {"filename": "OLD-VS", "similarity": 0.9999}, {"filename": "OLD-VolumeDiscount", "similarity": 0.8485}, {"filename": "OLD-ButtonFilled", "similarity": 0.8259}, {"filename": "NEW-ButtonFilled", "similarity": 0.8259}, {"filename": "OLD-AdvancedSearch", "similarity": 0.8016}, {"filename": "OLD-Move", "similarity": 0.7915}, {"filename": "NEW-LogoBlock", "similarity": 0.7906}, {"filename": "OLD-LogoBlock", "similarity": 0.7902}, {"filename": "OLD-Support", "similarity": 0.79}, {"filename": "OLD-Title", "similarity": 0.7897}, {"filename": "NEW-Title", "similarity": 0.7897}, {"filename": "OLD-AdsManagement", "similarity": 0.7859}, {"filename": "NEW-ImportStore", "similarity": 0.7815}, {"filename": "OLD-ImportStore", "similarity": 0.7814}, {"filename": "NEW-HideFilled", "similarity": 0.7791}, {"filename": "OLD-HideFilled", "similarity": 0.779}, {"filename": "NEW-Column", "similarity": 0.7762}, {"filename": "OLD-Column", "similarity": 0.7762}, {"filename": "OLD-AccountManagement", "similarity": 0.7754}, {"filename": "OLD-ViewportWide", "similarity": 0.7753}, {"filename": "NEW-ViewportWide", "similarity": 0.7753}, {"filename": "OLD-InsertDynamicSource", "similarity": 0.775}, {"filename": "NEW-InsertDynamicSource", "similarity": 0.775}, {"filename": "OLD-MemberCenter", "similarity": 0.7743}, {"filename": "OLD-FinancesFilled", "similarity": 0.7731}, {"filename": "NEW-FinancesFilled", "similarity": 0.7731}, {"filename": "OLD-MediaLibrary", "similarity": 0.7709}, {"filename": "NEW-CalendarTime", "similarity": 0.7709}, {"filename": "OLD-PictureTheme", "similarity": 0.7705}]