[{"filename": "NEW-SectionOutlined", "similarity": 1.0}, {"filename": "OLD-SectionOutlined", "similarity": 1.0}, {"filename": "NEW-BalanceFilled", "similarity": 0.9185}, {"filename": "OLD-BalanceFilled", "similarity": 0.9185}, {"filename": "NEW-TextBlockFilled", "similarity": 0.904}, {"filename": "OLD-TextBlockFilled", "similarity": 0.904}, {"filename": "OLD-SearchListFilled", "similarity": 0.8652}, {"filename": "NEW-SearchListFilled", "similarity": 0.8652}, {"filename": "NEW-BlogFilled", "similarity": 0.8449}, {"filename": "OLD-BlogFilled", "similarity": 0.8449}, {"filename": "OLD-ListFilled", "similarity": 0.8393}, {"filename": "NEW-ListFilled", "similarity": 0.8393}, {"filename": "OLD-ManageStoreFilled", "similarity": 0.8173}, {"filename": "NEW-ManageStoreFilled", "similarity": 0.8173}, {"filename": "OLD-ImageFilled", "similarity": 0.802}, {"filename": "NEW-ImageFilled", "similarity": 0.8018}, {"filename": "OLD-VolumeDiscountFilled", "similarity": 0.8017}, {"filename": "NEW-ImagesFilled", "similarity": 0.7993}, {"filename": "OLD-ImagesFilled", "similarity": 0.7993}, {"filename": "OLD-PreferenceFilled", "similarity": 0.7954}, {"filename": "OLD-InstagramFilled", "similarity": 0.7932}, {"filename": "OLD-VideoFilled", "similarity": 0.7915}, {"filename": "NEW-VideoFilled", "similarity": 0.7915}, {"filename": "OLD-DesktopFilled", "similarity": 0.7833}, {"filename": "NEW-DesktopFilled", "similarity": 0.7833}, {"filename": "OLD-TextFilled", "similarity": 0.7822}, {"filename": "NEW-TextFilled", "similarity": 0.7822}, {"filename": "NEW-HeaderOutlined", "similarity": 0.777}, {"filename": "OLD-HeaderOutlined", "similarity": 0.777}, {"filename": "NEW-MessageTipsFilled", "similarity": 0.7726}]