[{"filename": "OLD-ArrowUpOutlined", "similarity": 1.0}, {"filename": "NEW-ArrowUpOutlined", "similarity": 0.9999}, {"filename": "NEW-FallingOutlined", "similarity": 0.9076}, {"filename": "OLD-FallingOutlined", "similarity": 0.9076}, {"filename": "OLD-ArrowDownOutlined", "similarity": 0.9016}, {"filename": "NEW-ArrowDownOutlined", "similarity": 0.9014}, {"filename": "NEW-RefreshOutlined", "similarity": 0.894}, {"filename": "OLD-RefreshOutlined", "similarity": 0.894}, {"filename": "NEW-ImportOutlined", "similarity": 0.8898}, {"filename": "OLD-ImportOutlined", "similarity": 0.8898}, {"filename": "NEW-MoveUpOutlined", "similarity": 0.8888}, {"filename": "OLD-MoveUpOutlined", "similarity": 0.8888}, {"filename": "NEW-ExportOutlined", "similarity": 0.8875}, {"filename": "OLD-ExportOutlined", "similarity": 0.8875}, {"filename": "OLD-FullscreenOutlined", "similarity": 0.8818}, {"filename": "OLD-ToTopOutlined", "similarity": 0.8785}, {"filename": "NEW-ToTopOutlined", "similarity": 0.8785}, {"filename": "OLD-FilterOutlined", "similarity": 0.876}, {"filename": "OLD-SortOutlined", "similarity": 0.8759}, {"filename": "NEW-SortOutlined", "similarity": 0.8755}, {"filename": "NEW-FavoriteFilled", "similarity": 0.8705}, {"filename": "NEW-MoveDownOutlined", "similarity": 0.8659}, {"filename": "OLD-MoveDownOutlined", "similarity": 0.8659}, {"filename": "OLD-WithdrawOutlined", "similarity": 0.8589}, {"filename": "OLD-NewsOutlined", "similarity": 0.8586}, {"filename": "OLD-FullscreenExitOutlined", "similarity": 0.8571}, {"filename": "OLD-FavoriteFilled", "similarity": 0.8559}, {"filename": "OLD-PinOutlined", "similarity": 0.8487}, {"filename": "NEW-PinOutlined", "similarity": 0.8487}, {"filename": "OLD-Product3DOutlined", "similarity": 0.8483}]