[{"filename": "OLD-MultiCurrencyFilled", "similarity": 1.0}, {"filename": "NEW-InfoFilled", "similarity": 0.9281}, {"filename": "OLD-InfoFilled", "similarity": 0.9281}, {"filename": "OLD-AlertFilled", "similarity": 0.9275}, {"filename": "NEW-AlertFilled", "similarity": 0.9275}, {"filename": "OLD-CirclePlusOutlineFilled", "similarity": 0.9203}, {"filename": "NEW-CirclePlusOutlineFilled", "similarity": 0.9203}, {"filename": "NEW-ChatFilled", "similarity": 0.9151}, {"filename": "OLD-ChatFilled", "similarity": 0.9151}, {"filename": "NEW-CircleRightFilled", "similarity": 0.8954}, {"filename": "OLD-CircleRightFilled", "similarity": 0.8954}, {"filename": "OLD-BundleSalesFilled1Outlined", "similarity": 0.8751}, {"filename": "OLD-ProductRecommendationFilled", "similarity": 0.8672}, {"filename": "OLD-PlayCircleFilled", "similarity": 0.8517}, {"filename": "NEW-PlayCircleFilled", "similarity": 0.8517}, {"filename": "NEW-RadioSelectionFilled", "similarity": 0.8477}, {"filename": "OLD-RadioSelectionFilled", "similarity": 0.8477}, {"filename": "NEW-CircleTickFilled", "similarity": 0.8425}, {"filename": "OLD-CircleTickFilled", "similarity": 0.8425}, {"filename": "OLD-DuplicateFilled", "similarity": 0.842}, {"filename": "NEW-DuplicateFilled", "similarity": 0.842}, {"filename": "OLD-ToggleFilled", "similarity": 0.8418}, {"filename": "NEW-ToggleFilled", "similarity": 0.8418}, {"filename": "NEW-ClokcFilled", "similarity": 0.832}, {"filename": "OLD-ClokcFilled", "similarity": 0.832}, {"filename": "OLD-ShowFilled", "similarity": 0.8311}, {"filename": "NEW-ShowFilled", "similarity": 0.8311}, {"filename": "OLD-CashDollarFilled", "similarity": 0.8292}, {"filename": "NEW-CashDollarFilled", "similarity": 0.8292}, {"filename": "NEW-UndoOutlined", "similarity": 0.8238}]